alignak_backend_import/__init__.py
alignak_backend_import/cfg_to_backend.py
alignak_backend_import-1.2.2.dist-info/METADATA
alignak_backend_import-1.2.2.dist-info/RECORD
alignak_backend_import-1.2.2.dist-info/WHEEL
alignak_backend_import-1.2.2.dist-info/dependency_links.txt
alignak_backend_import-1.2.2.dist-info/entry_points.txt
alignak_backend_import-1.2.2.dist-info/top_level.txt
