Metadata-Version: 2.1
Name: alignak-backend-import
Version: 1.2.2
Summary: Alignak backend import
Requires-Dist: future
Requires-Dist: requests
Requires-Dist: alignak-backend-client
